dataset_orm/__init__.py
dataset_orm/columns.py
dataset_orm/files.py
dataset_orm/model.py
dataset_orm/query.py
dataset_orm/util.py
tests/__init__.py
tests/examples.py
tests/test_files.py
tests/test_models.py
dataset_orm-0.3.dist-info/LICENSE
dataset_orm-0.3.dist-info/METADATA
dataset_orm-0.3.dist-info/WHEEL
dataset_orm-0.3.dist-info/top_level.txt
dataset_orm-0.3.dist-info/RECORD
