Metadata-Version: 2.1
Name: dataset-orm
Version: 0.3
Summary: ORM for the dataset library
Home-page: 
Author: patrick
Author-email: patrick@productaize.io
License: MIT
Platform: UNKNOWN
License-File: LICENSE
Requires-Dist: dataset
Provides-Extra: mssql
Requires-Dist: pyodbc ; extra == 'mssql'
